{
  "nextCache": 1576525088634,
  "garages": {
    "A": {
      "space": 1423,
      "total": 1623,
      "percentage": 12
    },
    "B": {
      "space": 656,
      "total": 1259,
      "percentage": 48
    },
    "C": {
      "space": 1364,
      "total": 1852,
      "percentage": 26
    },
    "D": {
      "space": 1103,
      "total": 1241,
      "percentage": 11
    },
    "H": {
      "space": 1137,
      "total": 1284,
      "percentage": 11
    },
    "I": {
      "space": 956,
      "total": 1231,
      "percentage": 22
    },
    "Libra": {
      "space": 839,
      "total": 1007,
      "percentage": 17
    }
  }
}